{
    "JH": {
        "formKey": "JH",
        "formName": "结婚",
        "fields": [
            {
                "fieldKey": "JH_JHZ",
                "fieldName": "是否有结婚证"
            },
            {
                "fieldKey": "JH_SHHJ",
                "fieldName": "是否在沪户籍"
            },
            {
                "fieldKey": "JH_SHJH",
                "fieldName": "是否在沪结婚登记"
            }
        ],
        "docs": [
            {
                "docKey": "JHZ",
                "docName": "结婚证"
            },
            {
                "docKey": "BR2CZP",
                "docName": "本人2寸照片",
                "uploadAlone": true,
                "needCrop": true
            },
            {
                "docKey": "PO2CZP",
                "docName": "配偶2寸照片",
                "uploadAlone": true,
                "needCrop": true
            },
            {
                "docKey": "POSFZ",
                "docName": "配偶身份证"
            }
        ]
    }, 
        
    "XL": {
        "formKey": "XL",
        "formName": "学历",
        "fields": [
            {
                "fieldKey": "XL_BYZ",
                "fieldName": "是否有毕业证"
            },
            {
                "fieldKey": "XL_SHHJ",
                "fieldName": "是否在沪户籍"
            },
            {
                "fieldKey": "XL_SHBY",
                "fieldName": "是否在沪毕业"
            }
        ],
        "docs": [
            {
                "docKey": "BYZ",
                "docName": "毕业证"
            },
            {
                "docKey": "BR2CZP",
                "docName": "本人2寸照片",
                "uploadAlone": true,
                "needCrop": true
            },
            {
                "docKey": "TESTKEY",
                "docName": "测试文件上传",
                "uploadAlone": true
            }
        ]
    },
    
    "SGWSXSCF": {
        "formKey": "SGWSXSCF",
        "formName": "受过/未受刑事处分",
        "containsItem": false
    },
    
    "QSGX": {
        "formKey": "QSGX",
        "formName": "亲属关系",
        "containsVarItem": true,
        "fields": [
            {
                "fieldKey": "QSGX_SHHJ",
                "fieldName": "申请人户籍在上海"
            },
            {
                "fieldKey": "QSGX_RELATION_1",
                "fieldName": "和申请人关系/关系人姓名",
                "composite": true
            },
            {
                "fieldKey": "QSGX_RELATION_2",
                "fieldName": "和申请人关系/关系人姓名",
                "composite": true
            },
            {
                "fieldKey": "QSGX_RELATION_3",
                "fieldName": "和申请人关系/关系人姓名",
                "composite": true
            },
            {
                "fieldKey": "QSGX_RELATION_4",
                "fieldName": "和申请人关系/关系人姓名",
                "composite": true
            },
            {
                "fieldKey": "QSGX_RELATION_5",
                "fieldName": "和申请人关系/关系人姓名",
                "composite": true
            },
            {
                "fieldKey": "QSGX_RELATION_6",
                "fieldName": "和申请人关系/关系人姓名",
                "composite": true
            },
            {
                "fieldKey": "QSGX_RELATION_7",
                "fieldName": "和申请人关系/关系人姓名",
                "composite": true
            },
            {
                "fieldKey": "QSGX_RELATION_8",
                "fieldName": "和申请人关系/关系人姓名",
                "composite": true
            },
            {
                "fieldKey": "QSGX_RELATION_9",
                "fieldName": "和申请人关系/关系人姓名",
                "composite": true
            },
            {
                "fieldKey": "QSGX_RELATION_10",
                "fieldName": "和申请人关系/关系人姓名",
                "composite": true
            }
        ],
        "docs": [
            {
                "docKey": "QSZM",
                "docName": "与申报公证有关的亲属证明"
            }
        ]
    }, 
        
    "CYM": {
        "formKey": "CYM",
        "formName": "曾用名",
        "fields": [
            {
                "fieldKey": "CYM_CYM",
                "fieldName": "曾用名"
            },
            {
                "fieldKey": "CYM_SHHJ",
                "fieldName": "是否在沪户籍"
            }
        ],
        "docs": [
            {
                "docKey": "CYMYJ",
                "docName": "曾用名依据"
            }
        ]
    }, 
    
    "CS": {
        "formKey": "CS",
        "formName": "出生",
        "fields": [
            {
                "fieldKey": "CS_CSZ",
                "fieldName": "是否有出生证或独生子女证"
            },
            {
                "fieldKey": "CS_SHHJ",
                "fieldName": "是否在沪户籍"
            },
            {
                "fieldKey": "CS_SHCS",
                "fieldName": "出生地是否在上海"
            },
            {
                "fieldKey": "CS_SFJZ",
                "fieldName": "生父是否健在"
            },
            {
                "fieldKey": "CS_SMJZ",
                "fieldName": "生母是否健在"
            }
        ],
        "docs": [
            {
                "docKey": "CSZM",
                "docName": "出生证明"
            },
            {
                "docKey": "FMHYZM",
                "docName": "父母结婚证/离婚证+协议书/离婚判决书/离婚调解书"
            },
            {
                "docKey": "FQSFZ",
                "docName": "父亲身份证正反面",
                "dependent": true,
                "dependOn": "CS_SFJZ"
            },
            {
                "docKey": "MQSFZ",
                "docName": "母亲身份证正反面",
                "dependent": true,
                "dependOn": "CS_SMJZ"
            },
            {
                "docKey": "BRHKB",
                "docName": "本人户口本",
                "uploadAlone": true
            },
            {
                "docKey": "FQHKB",
                "docName": "父亲户口本",
                "uploadAlone": true,
                "dependent": true,
                "dependOn": "CS_SFJZ"
            },
            {
                "docKey": "MQHKB",
                "docName": "母亲户口本",
                "uploadAlone": true,
                "dependent": true,
                "dependOn": "CS_SMJZ"
            },
            {
                "docKey": "BR2CZP",
                "docName": "本人2寸照片",
                "uploadAlone": true,
                "needCrop": true
            }
        ]
    },
    
    "HKBFYJ": {
        "formKey": "HKBFYJ",
        "formName": "户口本复印件",
        "fields": [
            {
                "fieldKey": "HKBFYJ_SHHJ",
                "fieldName": "是否在沪户籍"
            }
        ],
        "docs": [
            {
                "docKey": "HKBSYY",
                "docName": "户口本所有有字页"
            }
        ]
    }
}
